repobot/__init__.py
repobot/cli.py
repobot/commands/__init__.py
repobot/commands/base.py
repobot/commands/colors.py
repobot/commands/deleteafter.py
repobot/commands/hello.py
repobot/commands/login.py
repobot/commands/ls.py
repobot/commands/whoami.py
repobot/commands/new/__init__.py
repobot/commands/new/git-clone.sh
repobot/commands/new/new.py
repobot/commands/utils/__init__.py
repobot/commands/utils/utils.py
repobot-0.1.4b0.dist-info/LICENSE
repobot-0.1.4b0.dist-info/METADATA
repobot-0.1.4b0.dist-info/WHEEL
repobot-0.1.4b0.dist-info/entry_points.txt
repobot-0.1.4b0.dist-info/top_level.txt
repobot-0.1.4b0.dist-info/RECORD
