Metadata-Version: 2.1
Name: repobot
Version: 0.1.4b0
Summary: Programatic github repo automation
Home-page: https://github.com/nickpalenchar/repobot
Author: Nick Palenchar
Author-email: 
License: MIT
Keywords: cli
Platform: UNKNOWN
Classifier: Development Status :: 4 - Beta
Classifier: Intended Audience :: Developers
Classifier: License :: OSI Approved :: GNU General Public License v3 (GPLv3)
Requires-Dist: docopt
Requires-Dist: keyring
Requires-Dist: requests (>=2.0.0)
Requires-Dist: colorama
Provides-Extra: test
Requires-Dist: coverage; extra == 'test'
Requires-Dist: pytest; extra == 'test'
Requires-Dist: pytest-cov; extra == 'test'
